ftrack.py
FTrackCore/__init__.py
FTrackCore/api/__init__.py
FTrackCore/api/_python_compatibility.py
FTrackCore/api/_python_ntpath.py
FTrackCore/api/action.py
FTrackCore/api/cache.py
FTrackCore/api/client.py
FTrackCore/api/component.py
FTrackCore/api/data.py
FTrackCore/api/ftlist.py
FTrackCore/api/ftobject.py
FTrackCore/api/ftrackerror.py
FTrackCore/api/group.py
FTrackCore/api/registry.py
FTrackCore/api/review_session.py
FTrackCore/api/review_session_invitee.py
FTrackCore/api/review_session_object.py
FTrackCore/api/review_session_object_status.py
FTrackCore/api/temp_data.py
FTrackCore/api/timelog.py
FTrackCore/api/version_data.py
FTrackCore/api/xmlserver.py
FTrackCore/api/accessor/__init__.py
FTrackCore/api/accessor/base.py
FTrackCore/api/accessor/disk.py
FTrackCore/api/accessor/s3.py
FTrackCore/api/accessor/server.py
FTrackCore/api/event/__init__.py
FTrackCore/api/event/base.py
FTrackCore/api/event/expression.py
FTrackCore/api/event/hub.py
FTrackCore/api/event/subscriber.py
FTrackCore/api/event/subscription.py
FTrackCore/api/location/__init__.py
FTrackCore/api/location/base.py
FTrackCore/api/location/memory.py
FTrackCore/api/location/unmanaged.py
FTrackCore/api/location/unmanaged_memory.py
FTrackCore/api/resource_identifier_transformer/__init__.py
FTrackCore/api/resource_identifier_transformer/base.py
FTrackCore/api/resource_identifier_transformer/internal.py
FTrackCore/api/structure/__init__.py
FTrackCore/api/structure/base.py
FTrackCore/api/structure/classic.py
FTrackCore/api/structure/connect.py
FTrackCore/api/structure/entity_id.py
FTrackCore/api/structure/id.py
FTrackCore/api/structure/origin.py
FTrackCore/api/structure/standard.py
FTrackCore/api/xmlrpc27/__init__.py
FTrackCore/api/xmlrpc27/httplib.py
FTrackCore/api/xmlrpc27/socket.py
FTrackCore/api/xmlrpc27/urllib.py
FTrackCore/api/xmlrpc27/urllib2.py
FTrackCore/api/xmlrpc27/urlparse.py
FTrackCore/api/xmlrpc27/xmlrpclib.py
ftrack_python_legacy_api-3.6.3.dist-info/DESCRIPTION.rst
ftrack_python_legacy_api-3.6.3.dist-info/METADATA
ftrack_python_legacy_api-3.6.3.dist-info/RECORD
ftrack_python_legacy_api-3.6.3.dist-info/WHEEL
ftrack_python_legacy_api-3.6.3.dist-info/metadata.json
ftrack_python_legacy_api-3.6.3.dist-info/top_level.txt
