Metadata-Version: 2.0
Name: ftrack-python-legacy-api
Version: 3.6.3
Summary: The ftrack legacy python api.
Home-page: https://bitbucket.org/ftrack/ftrack-python-legacy-api
Author: ftrack
Author-email: support@ftrack.com
License: Apache License (2.0)
Keywords: ftrack,api
Platform: UNKNOWN
Requires-Dist: pyparsing (<3,>=2.0.1)
Requires-Dist: clique (<2,>=1.2.0)
Requires-Dist: requests (<3,>=2.2.0)
Requires-Dist: websocket-client (!=0.42.0,!=0.42.1,<1,>=0.40.0)
Requires-Dist: six (>=1.5.2)
